[{
  "_id": {
    "$oid": "6412a4778dddcfee8148be33"
  },
  "requested_date": {
    "$date": {
      "$numberLong": "1678991400000"
    }
  },
  "group_id": 19,
  "stu_id": 1,
  "appeal": "hello pc",
  "__v": 0,
  "date_of_reply": {
    "$date": {
      "$numberLong": "1678991400000"
    }
  },
  "reply": "hy"
},{
  "_id": {
    "$oid": "64138e0ea78b9a50aa19c8ac"
  },
  "requested_date": {
    "$date": {
      "$numberLong": "1679077800000"
    }
  },
  "group_id": 19,
  "stu_id": 1,
  "appeal": "can we meet??",
  "appeal_status": 1,
  "__v": 0,
  "date_of_reply": {
    "$date": {
      "$numberLong": "1679077800000"
    }
  },
  "reply": ""
},{
  "_id": {
    "$oid": "6413f1d11a04f051d9511289"
  },
  "requested_date": {
    "$date": {
      "$numberLong": "1679077800000"
    }
  },
  "group_id": 19,
  "stu_id": 1,
  "appeal": "hello project",
  "appeal_status": 0,
  "__v": 0,
  "date_of_reply": {
    "$date": {
      "$numberLong": "1679077800000"
    }
  },
  "reply": "okk"
},{
  "_id": {
    "$oid": "641805f082a285004dfd9172"
  },
  "requested_date": {
    "$date": {
      "$numberLong": "1679337000000"
    }
  },
  "group_id": 19,
  "stu_id": 1,
  "appeal": "hello",
  "appeal_status": 2,
  "__v": 0
},{
  "_id": {
    "$oid": "6418062082a285004dfd9174"
  },
  "requested_date": {
    "$date": {
      "$numberLong": "1679337000000"
    }
  },
  "group_id": 19,
  "stu_id": 1,
  "appeal": "hello",
  "appeal_status": 2,
  "__v": 0
},{
  "_id": {
    "$oid": "6418062b82a285004dfd917a"
  },
  "requested_date": {
    "$date": {
      "$numberLong": "1679337000000"
    }
  },
  "group_id": 19,
  "stu_id": 1,
  "appeal": "hie",
  "appeal_status": 2,
  "__v": 0
},{
  "_id": {
    "$oid": "6418066682a285004dfd917e"
  },
  "requested_date": {
    "$date": {
      "$numberLong": "1679337000000"
    }
  },
  "group_id": 19,
  "stu_id": 1,
  "appeal": "hello pc",
  "appeal_status": 2,
  "__v": 0
},{
  "_id": {
    "$oid": "6418067682a285004dfd9180"
  },
  "requested_date": {
    "$date": {
      "$numberLong": "1679337000000"
    }
  },
  "group_id": 19,
  "stu_id": 1,
  "appeal": "complain on krupa",
  "appeal_status": 2,
  "__v": 0
}]